LICENSE
MANIFEST.in
README.md
setup.py
dat/__init__.py
dat/db.py
dat/exceptions.py
dat/fields.py
dat/models.py
dat/utils.py
dat.egg-info/PKG-INFO
dat.egg-info/SOURCES.txt
dat.egg-info/dependency_links.txt
dat.egg-info/requires.txt
dat.egg-info/top_level.txt