Metadata-Version: 1.1
Name: dat
Version: 1.0.0
Summary: A thin orm for pymongo
Home-page: https://github.com/anthonyalmarza/dat
Author: Anthony Almarza
Author-email: anthony.almarza@gmail.com
License: MIT
Download-URL: https://github.com/anthonyalmarza/dat/tarball/v1.0.0
Keywords: mongo,pymongo,orm-ish,data,nosql
Platform: UNKNOWN
Classifier: Development Status :: 4 - Beta
Classifier: Framework :: Django
Classifier: Intended Audience :: Developers
Classifier: License :: OSI Approved :: MIT License
Classifier: Operating System :: POSIX
Classifier: Programming Language :: Python
Classifier: Topic :: Internet :: WWW/HTTP
